{
  "CityObjects": {
    "NL.IMBAG.Pand.0503100000019695": {
      "attributes": {},
      "children": [
        "NL.IMBAG.Pand.0503100000019695-0"
      ],
      "geometry": [],
      "type": "Building"
    },
    "NL.IMBAG.Pand.0503100000019695-0": {
      "attributes": {},
      "geometry": [
        {
          "boundaries": [
            [
              [
                [
                  0,
                  1,
                  2,
                  3,
                  4,
                  5,
                  6,
                  7,
                  8,
                  9,
                  10,
                  11,
                  12,
                  13,
                  14,
                  15,
                  16,
                  17,
                  18,
                  19,
                  20,
                  21,
                  22
                ]
              ],
              [
                [
                  14,
                  23,
                  24,
                  15
                ]
              ],
              [
                [
                  15,
                  24,
                  25,
                  16
                ]
              ],
              [
                [
                  26,
                  1,
                  0,
                  27
                ]
              ],
              [
                [
                  27,
                  0,
                  22,
                  28
                ]
              ],
              [
                [
                  2,
                  1,
                  26,
                  29
                ]
              ],
              [
                [
                  3,
                  2,
                  29,
                  30
                ]
              ],
              [
                [
                  4,
                  3,
                  30,
                  31,
                  32
                ]
              ],
              [
                [
                  33,
                  34,
                  4,
                  32,
                  35
                ]
              ],
              [
                [
                  4,
                  34,
                  36,
                  5
                ]
              ],
              [
                [
                  5,
                  36,
                  37,
                  6
                ]
              ],
              [
                [
                  6,
                  37,
                  38,
                  7
                ]
              ],
              [
                [
                  7,
                  38,
                  39,
                  8
                ]
              ],
              [
                [
                  8,
                  39,
                  40,
                  9
                ]
              ],
              [
                [
                  9,
                  40,
                  41,
                  10
                ]
              ],
              [
                [
                  10,
                  41,
                  42,
                  11
                ]
              ],
              [
                [
                  11,
                  42,
                  43,
                  12
                ]
              ],
              [
                [
                  12,
                  43,
                  44,
                  13
                ]
              ],
              [
                [
                  13,
                  44,
                  23,
                  14
                ]
              ],
              [
                [
                  16,
                  25,
                  45,
                  17
                ]
              ],
              [
                [
                  17,
                  45,
                  46,
                  47,
                  48,
                  18
                ]
              ],
              [
                [
                  48,
                  49,
                  50,
                  51,
                  19,
                  18
                ]
              ],
              [
                [
                  52,
                  20,
                  19,
                  51
                ]
              ],
              [
                [
                  53,
                  21,
                  20,
                  52
                ]
              ],
              [
                [
                  28,
                  22,
                  21,
                  53
                ]
              ],
              [
                [
                  36,
                  34,
                  33,
                  54,
                  55,
                  56,
                  57,
                  58,
                  59,
                  60,
                  61,
                  62,
                  63,
                  64,
                  65,
                  66,
                  67,
                  68,
                  69,
                  70,
                  71,
                  46,
                  45,
                  25,
                  24,
                  23,
                  44,
                  43,
                  42,
                  41,
                  40,
                  39,
                  38,
                  37
                ]
              ],
              [
                [
                  29,
                  26,
                  27
                ]
              ],
              [
                [
                  72,
                  27,
                  53
                ]
              ],
              [
                [
                  73,
                  27,
                  72
                ]
              ],
              [
                [
                  74,
                  27,
                  73
                ]
              ],
              [
                [
                  74,
                  31,
                  27
                ]
              ],
              [
                [
                  31,
                  29,
                  27
                ]
              ],
              [
                [
                  53,
                  27,
                  28
                ]
              ],
              [
                [
                  30,
                  29,
                  31
                ]
              ],
              [
                [
                  75,
                  31,
                  74
                ]
              ],
              [
                [
                  76,
                  31,
                  75,
                  77,
                  78,
                  79,
                  80,
                  81,
                  82,
                  83,
                  84,
                  85,
                  86,
                  87,
                  88,
                  89,
                  90,
                  91,
                  92,
                  93,
                  94,
                  95,
                  96,
                  97,
                  98,
                  99
                ]
              ],
              [
                [
                  76,
                  32,
                  31
                ]
              ],
              [
                [
                  35,
                  32,
                  76,
                  99
                ]
              ],
              [
                [
                  54,
                  33,
                  35,
                  100
                ]
              ],
              [
                [
                  100,
                  35,
                  101
                ]
              ],
              [
                [
                  102,
                  35,
                  99,
                  98
                ]
              ],
              [
                [
                  101,
                  35,
                  102
                ]
              ],
              [
                [
                  47,
                  46,
                  71,
                  103
                ]
              ],
              [
                [
                  104,
                  49,
                  48,
                  47
                ]
              ],
              [
                [
                  103,
                  105,
                  47
                ]
              ],
              [
                [
                  105,
                  104,
                  47
                ]
              ],
              [
                [
                  106,
                  107,
                  50,
                  49,
                  104,
                  108
                ]
              ],
              [
                [
                  109,
                  110,
                  73,
                  51,
                  50,
                  107
                ]
              ],
              [
                [
                  51,
                  73,
                  111
                ]
              ],
              [
                [
                  51,
                  111,
                  52
                ]
              ],
              [
                [
                  111,
                  112,
                  52
                ]
              ],
              [
                [
                  112,
                  53,
                  52
                ]
              ],
              [
                [
                  112,
                  72,
                  53
                ]
              ],
              [
                [
                  55,
                  54,
                  100,
                  113
                ]
              ],
              [
                [
                  56,
                  55,
                  113,
                  114
                ]
              ],
              [
                [
                  57,
                  56,
                  114,
                  115
                ]
              ],
              [
                [
                  116,
                  58,
                  57,
                  115
                ]
              ],
              [
                [
                  59,
                  58,
                  116,
                  117
                ]
              ],
              [
                [
                  60,
                  59,
                  117,
                  118
                ]
              ],
              [
                [
                  61,
                  60,
                  118,
                  119
                ]
              ],
              [
                [
                  62,
                  61,
                  119,
                  120
                ]
              ],
              [
                [
                  63,
                  62,
                  120,
                  121
                ]
              ],
              [
                [
                  64,
                  63,
                  121,
                  122,
                  123
                ]
              ],
              [
                [
                  65,
                  64,
                  123,
                  124
                ]
              ],
              [
                [
                  66,
                  65,
                  124,
                  125
                ]
              ],
              [
                [
                  67,
                  66,
                  125,
                  126
                ]
              ],
              [
                [
                  68,
                  67,
                  126,
                  127
                ]
              ],
              [
                [
                  128,
                  69,
                  68,
                  127
                ]
              ],
              [
                [
                  129,
                  70,
                  69,
                  128
                ]
              ],
              [
                [
                  103,
                  71,
                  70,
                  129,
                  130
                ]
              ],
              [
                [
                  111,
                  72,
                  112
                ]
              ],
              [
                [
                  73,
                  72,
                  111
                ]
              ],
              [
                [
                  77,
                  75,
                  73,
                  110,
                  131,
                  132,
                  133,
                  134,
                  135,
                  136
                ]
              ],
              [
                [
                  75,
                  74,
                  73
                ]
              ],
              [
                [
                  137,
                  78,
                  77,
                  136,
                  138
                ]
              ],
              [
                [
                  137,
                  79,
                  78
                ]
              ],
              [
                [
                  80,
                  79,
                  137
                ]
              ],
              [
                [
                  81,
                  80,
                  137
                ]
              ],
              [
                [
                  82,
                  81,
                  137
                ]
              ],
              [
                [
                  82,
                  137,
                  139,
                  83
                ]
              ],
              [
                [
                  84,
                  83,
                  139,
                  140
                ]
              ],
              [
                [
                  85,
                  84,
                  140
                ]
              ],
              [
                [
                  86,
                  85,
                  140,
                  141
                ]
              ],
              [
                [
                  87,
                  86,
                  141,
                  142
                ]
              ],
              [
                [
                  88,
                  87,
                  142
                ]
              ],
              [
                [
                  89,
                  88,
                  142,
                  143
                ]
              ],
              [
                [
                  143,
                  144,
                  145,
                  90,
                  89
                ]
              ],
              [
                [
                  146,
                  91,
                  90,
                  145,
                  147,
                  148
                ]
              ],
              [
                [
                  146,
                  102,
                  149,
                  92,
                  91
                ]
              ],
              [
                [
                  92,
                  149,
                  93
                ]
              ],
              [
                [
                  149,
                  94,
                  93
                ]
              ],
              [
                [
                  149,
                  95,
                  94
                ]
              ],
              [
                [
                  149,
                  102,
                  96,
                  95
                ]
              ],
              [
                [
                  96,
                  102,
                  97
                ]
              ],
              [
                [
                  102,
                  98,
                  97
                ]
              ],
              [
                [
                  113,
                  100,
                  101
                ]
              ],
              [
                [
                  113,
                  101,
                  102
                ]
              ],
              [
                [
                  148,
                  102,
                  146
                ]
              ],
              [
                [
                  113,
                  102,
                  148,
                  147
                ]
              ],
              [
                [
                  150,
                  103,
                  130
                ]
              ],
              [
                [
                  150,
                  151,
                  103
                ]
              ],
              [
                [
                  151,
                  105,
                  103
                ]
              ],
              [
                [
                  108,
                  104,
                  105,
                  152
                ]
              ],
              [
                [
                  153,
                  105,
                  154
                ]
              ],
              [
                [
                  152,
                  105,
                  153,
                  155,
                  156
                ]
              ],
              [
                [
                  157,
                  105,
                  151
                ]
              ],
              [
                [
                  154,
                  105,
                  157
                ]
              ],
              [
                [
                  108,
                  158,
                  106
                ]
              ],
              [
                [
                  158,
                  109,
                  107,
                  106
                ]
              ],
              [
                [
                  152,
                  158,
                  108
                ]
              ],
              [
                [
                  143,
                  110,
                  109,
                  158
                ]
              ],
              [
                [
                  142,
                  131,
                  110,
                  143
                ]
              ],
              [
                [
                  114,
                  113,
                  144
                ]
              ],
              [
                [
                  144,
                  113,
                  147,
                  145
                ]
              ],
              [
                [
                  115,
                  114,
                  159
                ]
              ],
              [
                [
                  159,
                  114,
                  144
                ]
              ],
              [
                [
                  117,
                  116,
                  115
                ]
              ],
              [
                [
                  160,
                  115,
                  159
                ]
              ],
              [
                [
                  117,
                  115,
                  160
                ]
              ],
              [
                [
                  118,
                  117,
                  160
                ]
              ],
              [
                [
                  119,
                  118,
                  121
                ]
              ],
              [
                [
                  118,
                  160,
                  159
                ]
              ],
              [
                [
                  118,
                  159,
                  121
                ]
              ],
              [
                [
                  120,
                  119,
                  121
                ]
              ],
              [
                [
                  121,
                  144,
                  161
                ]
              ],
              [
                [
                  122,
                  121,
                  161
                ]
              ],
              [
                [
                  121,
                  159,
                  144
                ]
              ],
              [
                [
                  123,
                  122,
                  161
                ]
              ],
              [
                [
                  123,
                  162,
                  124
                ]
              ],
              [
                [
                  123,
                  161,
                  162
                ]
              ],
              [
                [
                  124,
                  155,
                  125
                ]
              ],
              [
                [
                  124,
                  162,
                  155
                ]
              ],
              [
                [
                  125,
                  163,
                  126
                ]
              ],
              [
                [
                  125,
                  155,
                  164
                ]
              ],
              [
                [
                  125,
                  164,
                  157
                ]
              ],
              [
                [
                  125,
                  157,
                  163
                ]
              ],
              [
                [
                  127,
                  126,
                  128
                ]
              ],
              [
                [
                  126,
                  163,
                  165
                ]
              ],
              [
                [
                  126,
                  165,
                  128
                ]
              ],
              [
                [
                  128,
                  165,
                  129
                ]
              ],
              [
                [
                  129,
                  165,
                  150,
                  130
                ]
              ],
              [
                [
                  141,
                  132,
                  131,
                  142
                ]
              ],
              [
                [
                  140,
                  133,
                  132,
                  141
                ]
              ],
              [
                [
                  139,
                  134,
                  133,
                  140
                ]
              ],
              [
                [
                  166,
                  135,
                  134,
                  139
                ]
              ],
              [
                [
                  138,
                  136,
                  135,
                  166
                ]
              ],
              [
                [
                  166,
                  137,
                  138
                ]
              ],
              [
                [
                  139,
                  137,
                  166
                ]
              ],
              [
                [
                  152,
                  143,
                  158
                ]
              ],
              [
                [
                  156,
                  143,
                  152
                ]
              ],
              [
                [
                  156,
                  144,
                  143
                ]
              ],
              [
                [
                  167,
                  144,
                  156
                ]
              ],
              [
                [
                  161,
                  144,
                  167
                ]
              ],
              [
                [
                  165,
                  163,
                  151,
                  150
                ]
              ],
              [
                [
                  163,
                  157,
                  151
                ]
              ],
              [
                [
                  155,
                  153,
                  154,
                  164
                ]
              ],
              [
                [
                  164,
                  154,
                  157
                ]
              ],
              [
                [
                  155,
                  162,
                  167,
                  156
                ]
              ],
              [
                [
                  162,
                  161,
                  167
                ]
              ]
            ]
          ],
          "lod": "2.2",
          "type": "Solid"
        }
      ],
      "parents": [
        "NL.IMBAG.Pand.0503100000019695"
      ],
      "type": "BuildingPart"
    }
  },
  "transform": {
    "scale": [
      1.0,
      1.0,
      1.0
    ],
    "translate": [
      0.0,
      0.0,
      0.0
    ]
  },
  "type": "CityJSON",
  "version": "1.1",
  "vertices": [
    [
      84993.89700000001,
      446791.741,
      -0.137
    ],
    [
      84989.79500000001,
      446794.048,
      -0.137
    ],
    [
      84989.871,
      446794.184,
      -0.137
    ],
    [
      84990.979,
      446796.16099999996,
      -0.137
    ],
    [
      84992.83300000001,
      446799.247,
      -0.137
    ],
    [
      84993.18000000001,
      446799.05199999997,
      -0.137
    ],
    [
      84995.653,
      446797.667,
      -0.137
    ],
    [
      84995.85100000001,
      446797.557,
      -0.137
    ],
    [
      84996.818,
      446797.015,
      -0.137
    ],
    [
      84996.966,
      446796.933,
      -0.137
    ],
    [
      84996.997,
      446796.989,
      -0.137
    ],
    [
      84997.55,
      446797.967,
      -0.137
    ],
    [
      84997.68500000001,
      446798.206,
      -0.137
    ],
    [
      84997.82100000001,
      446798.447,
      -0.137
    ],
    [
      84998.38100000001,
      446799.43799999997,
      -0.137
    ],
    [
      84998.43900000001,
      446799.54099999997,
      -0.137
    ],
    [
      84998.591,
      446799.455,
      -0.137
    ],
    [
      84998.873,
      446799.298,
      -0.137
    ],
    [
      84999.15892073803,
      446799.13893641124,
      -0.137
    ],
    [
      85002.5,
      446797.273,
      -0.137
    ],
    [
      85002.31700000001,
      446796.946,
      -0.137
    ],
    [
      84998.06300000001,
      446789.399,
      -0.137
    ],
    [
      84997.899,
      446789.491,
      -0.137
    ],
    [
      84998.38100000001,
      446799.43799999997,
      -0.24
    ],
    [
      84998.43900000001,
      446799.54099999997,
      -0.24
    ],
    [
      84998.591,
      446799.455,
      -0.24
    ],
    [
      84989.79500000001,
      446794.048,
      7.597
    ],
    [
      84993.89700000001,
      446791.741,
      12.155000000000001
    ],
    [
      84997.899,
      446789.491,
      7.719
    ],
    [
      84989.871,
      446794.184,
      9.132
    ],
    [
      84990.979,
      446796.16099999996,
      9.152000000000001
    ],
    [
      84992.83300000001,
      446799.247,
      10.85
    ],
    [
      84992.83300000001,
      446799.247,
      10.849
    ],
    [
      84992.94200000001,
      446799.44,
      -0.24
    ],
    [
      84992.83300000001,
      446799.247,
      -0.24
    ],
    [
      84992.94200000001,
      446799.44,
      11.039
    ],
    [
      84993.18000000001,
      446799.05199999997,
      -0.24
    ],
    [
      84995.653,
      446797.667,
      -0.24
    ],
    [
      84995.85100000001,
      446797.557,
      -0.24
    ],
    [
      84996.818,
      446797.015,
      -0.24
    ],
    [
      84996.966,
      446796.933,
      -0.24
    ],
    [
      84996.997,
      446796.989,
      -0.24
    ],
    [
      84997.55,
      446797.967,
      -0.24
    ],
    [
      84997.68500000001,
      446798.206,
      -0.24
    ],
    [
      84997.82100000001,
      446798.447,
      -0.24
    ],
    [
      84998.873,
      446799.298,
      -0.24
    ],
    [
      85002.504,
      446797.278,
      -0.24
    ],
    [
      85002.504,
      446797.278,
      8.873
    ],
    [
      84999.15892073803,
      446799.13893641124,
      10.991887992997771
    ],
    [
      84998.87325506646,
      446799.2984758703,
      11.173
    ],
    [
      84998.87325506646,
      446799.2984758703,
      11.462442928184085
    ],
    [
      85002.5,
      446797.273,
      7.449
    ],
    [
      85002.31700000001,
      446796.946,
      7.452
    ],
    [
      84998.06300000001,
      446789.399,
      7.538
    ],
    [
      84993.56000000001,
      446800.537,
      -0.24
    ],
    [
      84994.79800000001,
      446802.732,
      -0.24
    ],
    [
      84995.142,
      446803.343,
      -0.24
    ],
    [
      84996.03600000001,
      446804.92699999997,
      -0.24
    ],
    [
      84995.951,
      446804.977,
      -0.24
    ],
    [
      84996.07100000001,
      446805.189,
      -0.24
    ],
    [
      84997.084,
      446806.983,
      -0.24
    ],
    [
      84997.133,
      446807.071,
      -0.24
    ],
    [
      84997.164,
      446807.125,
      -0.24
    ],
    [
      85001.209,
      446804.859,
      -0.24
    ],
    [
      85001.301,
      446804.808,
      -0.24
    ],
    [
      85001.69600000001,
      446804.587,
      -0.24
    ],
    [
      85003.13900000001,
      446803.779,
      -0.24
    ],
    [
      85005.232,
      446802.607,
      -0.24
    ],
    [
      85005.44200000001,
      446802.49,
      -0.24
    ],
    [
      85005.372,
      446802.36699999997,
      -0.24
    ],
    [
      85004.364,
      446800.578,
      -0.24
    ],
    [
      85002.71,
      446797.644,
      -0.24
    ],
    [
      84997.648,
      446792.105,
      11.487
    ],
    [
      84999.47,
      446795.49,
      11.542
    ],
    [
      84994.948,
      446793.632,
      12.146
    ],
    [
      84996.82500000001,
      446797.011,
      12.118
    ],
    [
      84992.83687902507,
      446799.24720343086,
      10.85075629225306
    ],
    [
      84996.82505732575,
      446797.01108986005,
      12.117993784383028
    ],
    [
      84996.818,
      446797.015,
      12.115760701693684
    ],
    [
      84996.8014545955,
      446797.0242736393,
      12.110504051427633
    ],
    [
      84996.80220595264,
      446797.02600580675,
      12.110311568404224
    ],
    [
      84996.8049840355,
      446797.03256221046,
      12.109569469272365
    ],
    [
      84996.82596639186,
      446797.08169734455,
      12.10404146383636
    ],
    [
      84997.31681320188,
      446798.23362166993,
      11.974224326148153
    ],
    [
      84997.37890489507,
      446798.37865747453,
      11.957939065002002
    ],
    [
      84997.48623399658,
      446798.63027727953,
      11.92960541866896
    ],
    [
      84997.53046781267,
      446798.7337671914,
      11.917970413283754
    ],
    [
      84997.67350921003,
      446799.0686939572,
      11.880292456099987
    ],
    [
      84997.81605042865,
      446799.4031328082,
      11.842609431056339
    ],
    [
      84997.83681854003,
      446799.45292584086,
      11.8369056605674
    ],
    [
      84997.86150503805,
      446799.51071396377,
      11.830405994752756
    ],
    [
      84996.64866623693,
      446799.44710807595,
      11.593939207446715
    ],
    [
      84997.11046933863,
      446798.9024080158,
      11.797902462215593
    ],
    [
      84997.21617491366,
      446798.7770826642,
      11.844718276008152
    ],
    [
      84997.00600000001,
      446798.589,
      11.839196761697114
    ],
    [
      84996.78330748816,
      446798.3900795722,
      11.833273493339075
    ],
    [
      84995.49833110292,
      446798.6689968662,
      11.51339441899066
    ],
    [
      84995.01651747113,
      446798.77309863677,
      11.393549121679456
    ],
    [
      84993.27308480939,
      446799.15218983346,
      10.959410574526306
    ],
    [
      84993.09484752247,
      446799.1908200054,
      10.915052219168562
    ],
    [
      84993.56000000001,
      446800.537,
      12.115
    ],
    [
      84993.81700000001,
      446800.392,
      12.112
    ],
    [
      84994.21500000001,
      446800.16599999997,
      12.107000000000001
    ],
    [
      85002.71,
      446797.644,
      8.868
    ],
    [
      84998.94,
      446799.423,
      11.173
    ],
    [
      84998.975,
      446799.48699999996,
      11.173
    ],
    [
      84998.873,
      446799.298,
      12.794
    ],
    [
      84998.873,
      446799.298,
      11.462856841689344
    ],
    [
      84998.94,
      446799.423,
      12.791
    ],
    [
      84998.591,
      446799.455,
      11.775029612123753
    ],
    [
      84998.43900000001,
      446799.54099999997,
      11.943
    ],
    [
      85000.978,
      446794.572,
      9.182
    ],
    [
      84999.119,
      446791.273,
      9.149000000000001
    ],
    [
      84994.79800000001,
      446802.732,
      9.961
    ],
    [
      84995.142,
      446803.343,
      9.362
    ],
    [
      84996.03600000001,
      446804.92699999997,
      7.809
    ],
    [
      84995.951,
      446804.977,
      7.808
    ],
    [
      84996.07100000001,
      446805.189,
      7.599
    ],
    [
      84997.084,
      446806.983,
      7.6080000000000005
    ],
    [
      84997.133,
      446807.071,
      7.6080000000000005
    ],
    [
      84997.164,
      446807.125,
      7.609
    ],
    [
      85001.209,
      446804.859,
      12.135
    ],
    [
      85001.209,
      446804.859,
      12.163
    ],
    [
      85001.301,
      446804.808,
      12.06
    ],
    [
      85001.69600000001,
      446804.587,
      11.618
    ],
    [
      85003.13900000001,
      446803.779,
      10.005
    ],
    [
      85005.232,
      446802.607,
      7.664000000000001
    ],
    [
      85005.44200000001,
      446802.49,
      7.43
    ],
    [
      85005.372,
      446802.36699999997,
      7.432
    ],
    [
      85004.364,
      446800.578,
      7.466
    ],
    [
      85004.364,
      446800.578,
      8.827
    ],
    [
      84998.38100000001,
      446799.43799999997,
      11.948672086482997
    ],
    [
      84997.82100000001,
      446798.447,
      12.003614796260244
    ],
    [
      84997.68500000001,
      446798.206,
      12.016941257677043
    ],
    [
      84997.55,
      446797.967,
      12.030181363010026
    ],
    [
      84996.997,
      446796.989,
      12.084468546842
    ],
    [
      84996.966,
      446796.933,
      12.087451785578374
    ],
    [
      84996.818,
      446797.015,
      12.129
    ],
    [
      84996.966,
      446796.933,
      12.295
    ],
    [
      84997.55,
      446797.967,
      12.3
    ],
    [
      84997.68500000001,
      446798.206,
      12.301
    ],
    [
      84997.82100000001,
      446798.447,
      12.302
    ],
    [
      84998.38100000001,
      446799.43799999997,
      12.307
    ],
    [
      84998.43900000001,
      446799.54099999997,
      12.308
    ],
    [
      84996.58600000001,
      446802.671,
      9.238
    ],
    [
      84997.2406207773,
      446799.4781524275,
      11.316928613254976
    ],
    [
      84996.84196702339,
      446799.45724550565,
      11.503565905570202
    ],
    [
      84997.18512701933,
      446799.47524212336,
      11.342918968179369
    ],
    [
      84996.91156107603,
      446799.4608952829,
      11.470901767170805
    ],
    [
      84997.00600000001,
      446798.589,
      12.074
    ],
    [
      85004.23300000001,
      446800.642,
      8.908
    ],
    [
      85002.174,
      446801.967,
      10.259
    ],
    [
      84998.975,
      446799.48699999996,
      12.790000000000001
    ],
    [
      85001.33600000001,
      446803.912,
      11.176
    ],
    [
      85001.538,
      446802.377,
      10.677
    ],
    [
      85001.33600000001,
      446803.912,
      11.614
    ],
    [
      85001.33600000001,
      446803.912,
      12.694
    ],
    [
      85001.63900000001,
      446802.312,
      10.611
    ],
    [
      84998.591,
      446799.455,
      12.478
    ],
    [
      84996.304,
      446804.051,
      8.341
    ],
    [
      84996.15500000001,
      446804.779,
      7.8660000000000005
    ],
    [
      85001.212,
      446804.83499999996,
      12.149000000000001
    ],
    [
      85001.23700000001,
      446804.668,
      12.051
    ],
    [
      85002.174,
      446801.967,
      9.991
    ],
    [
      85001.538,
      446802.377,
      10.727
    ],
    [
      85004.23300000001,
      446800.642,
      7.6080000000000005
    ],
    [
      84996.997,
      446796.989,
      12.295
    ],
    [
      85001.23700000001,
      446804.668,
      12.249
    ]
  ]
}